spanner_nlp/StanfordCoreNLP.py
spanner_nlp/StanfordCoreNLPTest.py
spanner_nlp/__init__.py
spanner_nlp-0.0.6.dist-info/METADATA
spanner_nlp-0.0.6.dist-info/WHEEL
spanner_nlp-0.0.6.dist-info/top_level.txt
spanner_nlp-0.0.6.dist-info/RECORD
