Metadata-Version: 2.1
Name: spanner-nlp
Version: 0.0.6
Summary: spanner nlp
Home-page: https://github.com/DeanLight/spanner_NLP
Author: dean
Author-email: 
License: UNKNOWN
Platform: UNKNOWN
Classifier: Programming Language :: Python :: 3
Classifier: Operating System :: OS Independent
Requires-Python: >=3.8
Requires-Dist: psutil
Requires-Dist: requests
